cancerify/__init__.py
cancerify/cancerify.py
cancerify-1.0.0.data/scripts/cancerify
cancerify-1.0.0.dist-info/LICENSE
cancerify-1.0.0.dist-info/METADATA
cancerify-1.0.0.dist-info/WHEEL
cancerify-1.0.0.dist-info/top_level.txt
cancerify-1.0.0.dist-info/RECORD
