Metadata-Version: 2.1
Name: cancerify
Version: 1.0.0
Summary: Turn an innocent text into torturous hell
Home-page: https://github.com/i-abh-esc-wq/Cancerify
Author: Aniket Bhattacharyea
Author-email: i_abh_esc_wq@protonmail.com
License: UNKNOWN
Platform: UNKNOWN
Classifier: Programming Language :: Python :: 3
Classifier: License :: OSI Approved :: GNU General Public License v3 (GPLv3)
Classifier: Operating System :: OS Independent
Requires-Dist: emoji
Requires-Dist: bidict
